{
  "month": "August",
  "days": [
    { "day": 1,  "readings": [ { "book": "Luke", "verses": "13:1-9" },    { "book": "1 Timothy", "verses": "1:1-11" },    { "book": "Proverbs", "verses": "1" },       { "book": "Ezra", "verses": "1-2" } ] },
    { "day": 2,  "readings": [ { "book": "Luke", "verses": "13:10-21" },  { "book": "1 Timothy", "verses": "1:12-20" },   { "book": "Proverbs", "verses": "2" },       { "book": "Ezra", "verses": "3" } ] },
    { "day": 3,  "readings": [] },
    { "day": 4,  "readings": [ { "book": "Luke", "verses": "13:22-35" },  { "book": "1 Timothy", "verses": "2" },         { "book": "Proverbs", "verses": "3" },       { "book": "Ezra", "verses": "4-5" } ] },
    { "day": 5,  "readings": [ { "book": "Luke", "verses": "14:1-14" },   { "book": "1 Timothy", "verses": "3:1-10" },    { "book": "Proverbs", "verses": "4" },       { "book": "Ezra", "verses": "6" } ] },
    { "day": 6,  "readings": [ { "book": "Luke", "verses": "14:15-24" },  { "book": "1 Timothy", "verses": "3:11-16" },   { "book": "Proverbs", "verses": "5" },       { "book": "Ezra", "verses": "7" } ] },
    { "day": 7,  "readings": [ { "book": "Luke", "verses": "14:25-35" },  { "book": "1 Timothy", "verses": "4" },         { "book": "Proverbs", "verses": "6" },       { "book": "Ezra", "verses": "8" } ] },
    { "day": 8,  "readings": [ { "book": "Luke", "verses": "15:1-10" },   { "book": "1 Timothy", "verses": "5:1-15" },    { "book": "Proverbs", "verses": "7" },       { "book": "Ezra", "verses": "9" } ] },
    { "day": 9,  "readings": [ { "book": "Luke", "verses": "15:11-32" },  { "book": "1 Timothy", "verses": "5:16-25" },   { "book": "Proverbs", "verses": "8" },       { "book": "Ezra", "verses": "10" } ] },
    { "day": 10, "readings": [] },
    { "day": 11, "readings": [ { "book": "Luke", "verses": "16:1-9" },    { "book": "1 Timothy", "verses": "6:1-10" },    { "book": "Proverbs", "verses": "9" },       { "book": "Nehemiah", "verses": "1-2" } ] },
    { "day": 12, "readings": [ { "book": "Luke", "verses": "16:10-18" },  { "book": "1 Timothy", "verses": "6:11-21" },   { "book": "Proverbs", "verses": "10:1-16" }, { "book": "Nehemiah", "verses": "3" } ] },
    { "day": 13, "readings": [ { "book": "Luke", "verses": "16:19-31" },  { "book": "2 Timothy", "verses": "1:1-7" },     { "book": "Proverbs", "verses": "10:17-32" },{ "book": "Nehemiah", "verses": "4-5" } ] },
    { "day": 14, "readings": [ { "book": "Luke", "verses": "17:1-10" },   { "book": "2 Timothy", "verses": "1:8-18" },    { "book": "Proverbs", "verses": "11-15" },   { "book": "Nehemiah", "verses": "6" } ] },
    { "day": 15, "readings": [ { "book": "Luke", "verses": "17:11-19" },  { "book": "2 Timothy", "verses": "2:1-13" },    { "book": "Proverbs", "verses": "11:16-31" },{ "book": "Nehemiah", "verses": "7" } ] },
    { "day": 16, "readings": [ { "book": "Luke", "verses": "17:20-37" },  { "book": "2 Timothy", "verses": "2:14-26" },   { "book": "Proverbs", "verses": "12:1-14" }, { "book": "Nehemiah", "verses": "8" } ] },
    { "day": 17, "readings": [] },
    { "day": 18, "readings": [ { "book": "Luke", "verses": "18:1-8" },    { "book": "2 Timothy", "verses": "3:1-9" },     { "book": "Proverbs", "verses": "12:15-28" },{ "book": "Nehemiah", "verses": "9" } ] },
    { "day": 19, "readings": [ { "book": "Luke", "verses": "18:9-17" },   { "book": "2 Timothy", "verses": "3:10-17" },   { "book": "Proverbs", "verses": "13:1-12" }, { "book": "Nehemiah", "verses": "10" } ] },
    { "day": 20, "readings": [ { "book": "Luke", "verses": "18:18-30" },  { "book": "2 Timothy", "verses": "4" },         { "book": "Proverbs", "verses": "13:13-25" },{ "book": "Nehemiah", "verses": "11" } ] },
    { "day": 21, "readings": [ { "book": "Luke", "verses": "18:31-43" },  { "book": "Titus", "verses": "1:1-9" },         { "book": "Proverbs", "verses": "14:1-18" }, { "book": "Nehemiah", "verses": "12" } ] },
    { "day": 22, "readings": [ { "book": "Luke", "verses": "19:1-10" },   { "book": "Titus", "verses": "1:10-16" },       { "book": "Proverbs", "verses": "14:19-35" },{ "book": "Nehemiah", "verses": "13" } ] },
    { "day": 23, "readings": [ { "book": "Luke", "verses": "19:11-27" },  { "book": "Titus", "verses": "2:1-10" },        { "book": "Proverbs", "verses": "15:1-17" }, { "book": "Esther", "verses": "1" } ] },
    { "day": 24, "readings": [] },
    { "day": 25, "readings": [ { "book": "Luke", "verses": "19:28-38" },  { "book": "Titus", "verses": "2:11-15" },       { "book": "Proverbs", "verses": "15:18-33" },{ "book": "Esther", "verses": "2" } ] },
    { "day": 26, "readings": [ { "book": "Luke", "verses": "19:39-48" },  { "book": "Titus", "verses": "3:1-8" },         { "book": "Proverbs", "verses": "16:1-16" }, { "book": "Esther", "verses": "3-4" } ] },
    { "day": 27, "readings": [ { "book": "Luke", "verses": "20:1-8" },    { "book": "Titus", "verses": "3:9-15" },        { "book": "Proverbs", "verses": "16:17-33" },{ "book": "Esther", "verses": "5-6" } ] },
    { "day": 28, "readings": [ { "book": "Luke", "verses": "20:9-19" },   { "book": "Philemon", "verses": "1-11" },       { "book": "Proverbs", "verses": "17:1-14" }, { "book": "Esther", "verses": "7-8" } ] },
    { "day": 29, "readings": [ { "book": "Luke", "verses": "20:20-26" },  { "book": "Philemon", "verses": "12-25" },      { "book": "Proverbs", "verses": "17:15-28" },{ "book": "Esther", "verses": "9-10" } ] },
    { "day": 30, "readings": [] },
    { "day": 31, "readings": [] }
  ]
}
